djamal/LICENSE
djamal/__init__.py
djamal/djamal.png
djamal/management/__init__.py
djamal/management/commands/__init__.py
djamal/management/commands/apps.py
djamal/management/commands/djamal.py
djamal/management/commands/forms.py
djamal/management/commands/templates/__init__.py
djamal/management/commands/templates/admin.py
djamal/management/commands/templates/edit_deploy_yaml.py
djamal/management/commands/urls.py
djamal/management/commands/views.py
djamal-0.2.9.dist-info/METADATA
djamal-0.2.9.dist-info/WHEEL
djamal-0.2.9.dist-info/entry_points.txt
djamal-0.2.9.dist-info/RECORD
