Metadata-Version: 2.1
Name: djamal
Version: 0.2.9
Summary: A Django extension to deploy web apps anywhere, from bare metal to cloud VMs.
Home-page: https://github.com/aitoehigie/djamal
Author: Ehigie (Pystar) Aito
Author-email: aitoehigie@gmail.com
Requires-Python: >=3.7
Classifier: Development Status :: 3 - Alpha
Classifier: Intended Audience :: Developers
Classifier: License :: OSI Approved :: MIT License
Classifier: Programming Language :: Python :: 3
Classifier: Programming Language :: Python :: 3.7
Classifier: Programming Language :: Python :: 3.8
Classifier: Programming Language :: Python :: 3.9
Classifier: Programming Language :: Python :: 3.10
Classifier: Programming Language :: Python :: 3.11
Classifier: Programming Language :: Python :: 3.6
Classifier: Topic :: Software Development :: Build Tools
Requires-Dist: ruamel-yaml (>=0.18.6,<0.19.0)
Project-URL: Repository, https://github.com/aitoehigie/djamal
